{
    "actorSpecification": 1,
    "fields": {},
    "views": {
        "hotels": {
            "title": "Overview",
            "description": "Overview of all scraped hotels",
            "transformation": {
                "fields": [
                    "title",
                    "url",
                    "prices"
                ]
            },
            "display": {
                "component": "table",
                "properties": {
                    "title": {
                        "label": "Hotel name",
                        "format": "text"
                    },
                    "url": {
                        "label": "URL",
                        "format": "link"
                    },
                    "prices": {
                        "label": "Prices",
                        "format": "array"
                    }
                }
            }
        }
    }
}
